FaceCropAnime/__init__.py
FaceCropAnime/crop.py
FaceCropAnime/face_crop.py
FaceCropAnime/models/__init__.py
FaceCropAnime/models/common.py
FaceCropAnime/models/experimental.py
FaceCropAnime/models/export.py
FaceCropAnime/models/yolo.py
FaceCropAnime/utils/__init__.py
FaceCropAnime/utils/activations.py
FaceCropAnime/utils/datasets.py
FaceCropAnime/utils/general.py
FaceCropAnime/utils/google_utils.py
FaceCropAnime/utils/torch_utils.py
FaceCropAnime-0.0.1.dist-info/METADATA
FaceCropAnime-0.0.1.dist-info/WHEEL
FaceCropAnime-0.0.1.dist-info/top_level.txt
FaceCropAnime-0.0.1.dist-info/RECORD
